qtlsearch/Annotations.py
qtlsearch/HOGAnnotations.py
qtlsearch/HOGParser.py
qtlsearch/HOGParser_HOGPROP.py
qtlsearch/HOGStore.py
qtlsearch/OBOParser.py
qtlsearch/OMARestAPI.py
qtlsearch/QTLs.py
qtlsearch/__init__.py
qtlsearch/_utils.py
qtlsearch/download.py
qtlsearch/main.py
qtlsearch/reuse_db.py
qtlsearch/parsers/__init__.py
qtlsearch/parsers/chebi_parser.py
qtlsearch/parsers/go_parser.py
qtlsearch/parsers/utils.py
qtlsearch/strategies/__init__.py
qtlsearch/strategies/sum.py
qtlsearch/strategies/utils.py
qtlsearch-1.0.3.data/scripts/qtlsearch-init
qtlsearch-1.0.3.data/scripts/qtlsearch-run
qtlsearch-1.0.3.dist-info/COPYING
qtlsearch-1.0.3.dist-info/COPYING.LESSER
qtlsearch-1.0.3.dist-info/METADATA
qtlsearch-1.0.3.dist-info/WHEEL
qtlsearch-1.0.3.dist-info/top_level.txt
qtlsearch-1.0.3.dist-info/RECORD
